README.rst
setup.py
pytest_testbook/__init__.py
pytest_testbook/hooks.py
pytest_testbook/plugin.py
pytest_testbook.egg-info/PKG-INFO
pytest_testbook.egg-info/SOURCES.txt
pytest_testbook.egg-info/dependency_links.txt
pytest_testbook.egg-info/entry_points.txt
pytest_testbook.egg-info/requires.txt
pytest_testbook.egg-info/top_level.txt