Metadata-Version: 1.1
Name: pytest-testbook
Version: 0.0.10
Summary: A plugin to run tests written in Jupyter notebook
Home-page: https://github.com/ldiary/pytest-testbook
Author: Ernesto D. Luzon Jr.
Author-email: please_raise_a_bug_in_myrepo@github.com
License: MIT
Platform: UNKNOWN
Classifier: Development Status :: 3 - Alpha
Classifier: Framework :: Pytest
Classifier: Intended Audience :: Developers
Classifier: Topic :: Software Development :: Testing
Classifier: Topic :: Software Development :: Quality Assurance
Classifier: Programming Language :: Python :: 3.5
Classifier: Programming Language :: Python :: Implementation :: CPython
Classifier: Operating System :: OS Independent
Classifier: License :: OSI Approved :: MIT License
